backtesting/__init__.py
backtesting/analysis.py
backtesting/report.py
backtesting/simulation.py
trading_research-0.0.3.dist-info/LICENSE
trading_research-0.0.3.dist-info/METADATA
trading_research-0.0.3.dist-info/WHEEL
trading_research-0.0.3.dist-info/top_level.txt
trading_research-0.0.3.dist-info/RECORD
