Metadata-Version: 2.1
Name: trading-research
Version: 0.0.3
Summary: Tools for researching quantitative trading strategies
Home-page: https://github.com/mhconradt/research-tools
Author: Maxwell Conradt
Author-email: mhconradt@protonmail.com
License: UNKNOWN
Platform: UNKNOWN
Classifier: Programming Language :: Python :: 3
Classifier: License :: OSI Approved :: MIT License
Classifier: Operating System :: OS Independent
Requires-Python: >=3.6
License-File: LICENSE
Requires-Dist: matplotlib
Requires-Dist: numba
Requires-Dist: numpy
Requires-Dist: pandas
